pycld2/__init__.py
pycld2/_pycld2.cp36-win32.pyd
pycld2-0.42.dist-info/LICENSE
pycld2-0.42.dist-info/METADATA
pycld2-0.42.dist-info/WHEEL
pycld2-0.42.dist-info/top_level.txt
pycld2-0.42.dist-info/RECORD
